LICENSE
MANIFEST.in
README.rst
setup.py
il2fb/maps/heightmaps/__init__.py
il2fb/maps/heightmaps/constants.py
il2fb/maps/heightmaps/creation.py
il2fb/maps/heightmaps/logging.py
il2fb/maps/heightmaps/rendering.py
il2fb_heightmap_creator.egg-info/PKG-INFO
il2fb_heightmap_creator.egg-info/SOURCES.txt
il2fb_heightmap_creator.egg-info/dependency_links.txt
il2fb_heightmap_creator.egg-info/entry_points.txt
il2fb_heightmap_creator.egg-info/namespace_packages.txt
il2fb_heightmap_creator.egg-info/requires.txt
il2fb_heightmap_creator.egg-info/top_level.txt
requirements/dist.txt