Metadata-Version: 1.1
Name: il2fb-heightmap-creator
Version: 1.0.0
Summary: Distributed creator of height maps for «IL-2 Sturmovik: Forgotten Battles»
Home-page: https://github.com/IL2HorusTeam/il2fb-heightmap-creator
Author: Alexander Oblovatniy
Author-email: oblovatniy@gmail.com
License: MIT
Platform: UNKNOWN
Classifier: Programming Language :: Python :: 3.6
Classifier: Operating System :: Unix
Classifier: Operating System :: Microsoft :: Windows
Classifier: License :: OSI Approved :: MIT License
Classifier: Natural Language :: English
